models/__init__.py
models/base.py
models/certification.py
models/contact.py
models/contact_request.py
models/past_experience.py
models/profile.py
models/programming_skill.py
models/project.py
models/resume.py
models/soft_skill.py
models/tech_stack.py
settings.py
data_manager_library-0.0.3.dist-info/METADATA
data_manager_library-0.0.3.dist-info/WHEEL
data_manager_library-0.0.3.dist-info/RECORD
