Metadata-Version: 2.1
Name: data-manager-library
Version: 0.0.3
Summary: 
Author: Aafaq Rana
Author-email: m.aafaq.rana@gmail.com
Requires-Python: >=3.12,<4.0
Classifier: Programming Language :: Python :: 3
Classifier: Programming Language :: Python :: 3.12
Requires-Dist: alembic (>=1.13.1,<2.0.0)
Requires-Dist: psycopg2 (>=2.9.9,<3.0.0)
Requires-Dist: pydantic (>=2.7.1,<3.0.0)
Requires-Dist: pydantic-settings (>=2.2.1,<3.0.0)
Requires-Dist: sqlalchemy (>=2.0.30,<3.0.0)
